<?xml version="1.0"?>
<XmlLevelData xmlns:xsi="http://www.w3.org/2001/XMLSchema-instance" xmlns:xsd="http://www.w3.org/2001/XMLSchema">
  <waypoints />
  <actor>
    <position>
      <X>-4</X>
      <Y>13.5911236</Y>
      <Z>6.491188</Z>
    </position>
    <orientation>5.89895153</orientation>
    <heightOffset>0</heightOffset>
    <color>Green</color>
    <tintable>true</tintable>
    <creatableId>00000000-0000-0000-0000-000000000000</creatableId>
    <creatableName>Дерево 1</creatableName>
    <brain StartTaskId="-1" ActiveTaskId="-1">
      <uniqueNum>4678</uniqueNum>
      <tasks>
        <Task upid="task.managed0">
          <reflexes />
        </Task>
        <Task upid="task.managed1">
          <reflexes />
        </Task>
        <Task upid="task.managed2">
          <reflexes />
        </Task>
        <Task upid="task.managed3">
          <reflexes />
        </Task>
        <Task upid="task.managed4">
          <reflexes />
        </Task>
        <Task upid="task.managed5">
          <reflexes />
        </Task>
        <Task upid="task.managed6">
          <reflexes />
        </Task>
        <Task upid="task.managed7">
          <reflexes />
        </Task>
        <Task upid="task.managed8">
          <reflexes />
        </Task>
        <Task upid="task.managed9">
          <reflexes />
        </Task>
        <Task upid="task.managed10">
          <reflexes />
        </Task>
        <Task upid="task.managed11">
          <reflexes />
        </Task>
      </tasks>
    </brain>
    <parameters>
      <uniqueNum>3702</uniqueNum>
      <immobile>false</immobile>
      <immobileNoRot>false</immobileNoRot>
      <invulnerable>false</invulnerable>
      <showSensors>false</showSensors>
      <showHitPoints>false</showHitPoints>
      <creatable>false</creatable>
      <mute>false</mute>
      <maxHitPoints>50</maxHitPoints>
      <blipDamage>5</blipDamage>
      <missileDamage>50</missileDamage>
      <movementSpeedModifier>1</movementSpeedModifier>
      <turningSpeedModifier>1</turningSpeedModifier>
      <linearAccelerationModifier>1</linearAccelerationModifier>
      <turningAccelerationModifier>1</turningAccelerationModifier>
      <verticalSpeedModifier>1</verticalSpeedModifier>
      <verticalAccelerationModifier>1</verticalAccelerationModifier>
      <blipReloadTime>0.05</blipReloadTime>
      <blipSpeed>10</blipSpeed>
      <blipRange>35</blipRange>
      <blipsInAir>40</blipsInAir>
      <beamReloadTime>0.025</beamReloadTime>
      <beamSpeed>10</beamSpeed>
      <beamDist>35</beamDist>
      <beamsInAir>2000</beamsInAir>
      <revealed>false</revealed>
      <missileReloadTime>3</missileReloadTime>
      <missileSpeed>6</missileSpeed>
      <missileRange>50</missileRange>
      <missilesInAir>4</missilesInAir>
      <missileTrails>true</missileTrails>
      <shieldEffects>true</shieldEffects>
      <invisible>false</invisible>
      <ignored>false</ignored>
      <camouflaged>false</camouflaged>
      <pushRange>15</pushRange>
      <pushStrength>50</pushStrength>
      <kickStrength>10</kickStrength>
      <kickRate>2</kickRate>
      <hearing>1</hearing>
      <loudness>1</loudness>
      <glowAmt>1</glowAmt>
      <glowLights>0</glowLights>
      <glowEmission>0</glowEmission>
      <displayLOS>false</displayLOS>
      <displayLOP>false</displayLOP>
      <displayCurrentPage>false</displayCurrentPage>
      <cameraMode>UserControlled</cameraMode>
      <memoryLifetime>4</memoryLifetime>
      <coefficientOfRestitution>0.8</coefficientOfRestitution>
      <friction>0.5</friction>
      <lightRange>10</lightRange>
      <stayAboveWater>false</stayAboveWater>
      <maxCreated>100</maxCreated>
      <rescale>1</rescale>
      <holdDistance>1</holdDistance>
      <_holdDistance>1</_holdDistance>
      <mass>500</mass>
      <heightOffset>-666</heightOffset>
      <nearByDistance>5</nearByDistance>
      <farAwayDistance>15</farAwayDistance>
    </parameters>
    <version>1</version>
    <typename>Yucca1</typename>
  </actor>
  <actor>
    <position>
      <X>-12.0056076</X>
      <Y>10.8058405</Y>
      <Z>2.77515841</Z>
    </position>
    <orientation>5.898951</orientation>
    <heightOffset>0</heightOffset>
    <color>White</color>
    <tintable>true</tintable>
    <creatableId>00000000-0000-0000-0000-000000000000</creatableId>
    <creatableName>Octopus 1</creatableName>
    <brain StartTaskId="-1" ActiveTaskId="-1">
      <uniqueNum>4679</uniqueNum>
      <tasks>
        <Task upid="task.managed0">
          <reflexes />
        </Task>
        <Task upid="task.managed1">
          <reflexes />
        </Task>
        <Task upid="task.managed2">
          <reflexes />
        </Task>
        <Task upid="task.managed3">
          <reflexes />
        </Task>
        <Task upid="task.managed4">
          <reflexes />
        </Task>
        <Task upid="task.managed5">
          <reflexes />
        </Task>
        <Task upid="task.managed6">
          <reflexes />
        </Task>
        <Task upid="task.managed7">
          <reflexes />
        </Task>
        <Task upid="task.managed8">
          <reflexes />
        </Task>
        <Task upid="task.managed9">
          <reflexes />
        </Task>
        <Task upid="task.managed10">
          <reflexes />
        </Task>
        <Task upid="task.managed11">
          <reflexes />
        </Task>
      </tasks>
    </brain>
    <parameters>
      <uniqueNum>3754</uniqueNum>
      <immobile>false</immobile>
      <immobileNoRot>false</immobileNoRot>
      <invulnerable>false</invulnerable>
      <showSensors>false</showSensors>
      <showHitPoints>false</showHitPoints>
      <creatable>false</creatable>
      <mute>false</mute>
      <maxHitPoints>50</maxHitPoints>
      <blipDamage>5</blipDamage>
      <missileDamage>50</missileDamage>
      <movementSpeedModifier>1</movementSpeedModifier>
      <turningSpeedModifier>1</turningSpeedModifier>
      <linearAccelerationModifier>1</linearAccelerationModifier>
      <turningAccelerationModifier>1</turningAccelerationModifier>
      <verticalSpeedModifier>1</verticalSpeedModifier>
      <verticalAccelerationModifier>1</verticalAccelerationModifier>
      <blipReloadTime>0.05</blipReloadTime>
      <blipSpeed>10</blipSpeed>
      <blipRange>35</blipRange>
      <blipsInAir>40</blipsInAir>
      <beamReloadTime>0.025</beamReloadTime>
      <beamSpeed>10</beamSpeed>
      <beamDist>35</beamDist>
      <beamsInAir>2000</beamsInAir>
      <revealed>false</revealed>
      <missileReloadTime>3</missileReloadTime>
      <missileSpeed>6</missileSpeed>
      <missileRange>50</missileRange>
      <missilesInAir>4</missilesInAir>
      <missileTrails>true</missileTrails>
      <shieldEffects>true</shieldEffects>
      <invisible>false</invisible>
      <ignored>false</ignored>
      <camouflaged>false</camouflaged>
      <pushRange>15</pushRange>
      <pushStrength>50</pushStrength>
      <kickStrength>10</kickStrength>
      <kickRate>2</kickRate>
      <hearing>1</hearing>
      <loudness>1</loudness>
      <glowAmt>1</glowAmt>
      <glowLights>0</glowLights>
      <glowEmission>0</glowEmission>
      <displayLOS>false</displayLOS>
      <displayLOP>false</displayLOP>
      <displayCurrentPage>false</displayCurrentPage>
      <cameraMode>UserControlled</cameraMode>
      <memoryLifetime>4</memoryLifetime>
      <coefficientOfRestitution>0.4</coefficientOfRestitution>
      <friction>0.95</friction>
      <lightRange>10</lightRange>
      <stayAboveWater>false</stayAboveWater>
      <maxCreated>100</maxCreated>
      <rescale>1</rescale>
      <holdDistance>1</holdDistance>
      <_holdDistance>1</_holdDistance>
      <mass>10</mass>
      <heightOffset>-666</heightOffset>
      <nearByDistance>5</nearByDistance>
      <farAwayDistance>15</farAwayDistance>
    </parameters>
    <version>1</version>
    <typename>Octopus</typename>
  </actor>
  <actor>
    <position>
      <X>-7.876132</X>
      <Y>20.479681</Y>
      <Z>2.79041719</Z>
    </position>
    <orientation>5.898951</orientation>
    <heightOffset>0</heightOffset>
    <color>White</color>
    <tintable>true</tintable>
    <creatableId>00000000-0000-0000-0000-000000000000</creatableId>
    <creatableName>Octopus 2</creatableName>
    <brain StartTaskId="-1" ActiveTaskId="-1">
      <uniqueNum>4680</uniqueNum>
      <tasks>
        <Task upid="task.managed0">
          <reflexes />
        </Task>
        <Task upid="task.managed1">
          <reflexes />
        </Task>
        <Task upid="task.managed2">
          <reflexes />
        </Task>
        <Task upid="task.managed3">
          <reflexes />
        </Task>
        <Task upid="task.managed4">
          <reflexes />
        </Task>
        <Task upid="task.managed5">
          <reflexes />
        </Task>
        <Task upid="task.managed6">
          <reflexes />
        </Task>
        <Task upid="task.managed7">
          <reflexes />
        </Task>
        <Task upid="task.managed8">
          <reflexes />
        </Task>
        <Task upid="task.managed9">
          <reflexes />
        </Task>
        <Task upid="task.managed10">
          <reflexes />
        </Task>
        <Task upid="task.managed11">
          <reflexes />
        </Task>
      </tasks>
    </brain>
    <parameters>
      <uniqueNum>3783</uniqueNum>
      <immobile>false</immobile>
      <immobileNoRot>false</immobileNoRot>
      <invulnerable>false</invulnerable>
      <showSensors>false</showSensors>
      <showHitPoints>false</showHitPoints>
      <creatable>false</creatable>
      <mute>false</mute>
      <maxHitPoints>50</maxHitPoints>
      <blipDamage>5</blipDamage>
      <missileDamage>50</missileDamage>
      <movementSpeedModifier>1</movementSpeedModifier>
      <turningSpeedModifier>1</turningSpeedModifier>
      <linearAccelerationModifier>1</linearAccelerationModifier>
      <turningAccelerationModifier>1</turningAccelerationModifier>
      <verticalSpeedModifier>1</verticalSpeedModifier>
      <verticalAccelerationModifier>1</verticalAccelerationModifier>
      <blipReloadTime>0.05</blipReloadTime>
      <blipSpeed>10</blipSpeed>
      <blipRange>35</blipRange>
      <blipsInAir>40</blipsInAir>
      <beamReloadTime>0.025</beamReloadTime>
      <beamSpeed>10</beamSpeed>
      <beamDist>35</beamDist>
      <beamsInAir>2000</beamsInAir>
      <revealed>false</revealed>
      <missileReloadTime>3</missileReloadTime>
      <missileSpeed>6</missileSpeed>
      <missileRange>50</missileRange>
      <missilesInAir>4</missilesInAir>
      <missileTrails>true</missileTrails>
      <shieldEffects>true</shieldEffects>
      <invisible>false</invisible>
      <ignored>false</ignored>
      <camouflaged>false</camouflaged>
      <pushRange>15</pushRange>
      <pushStrength>50</pushStrength>
      <kickStrength>10</kickStrength>
      <kickRate>2</kickRate>
      <hearing>1</hearing>
      <loudness>1</loudness>
      <glowAmt>1</glowAmt>
      <glowLights>0</glowLights>
      <glowEmission>0</glowEmission>
      <displayLOS>false</displayLOS>
      <displayLOP>false</displayLOP>
      <displayCurrentPage>false</displayCurrentPage>
      <cameraMode>UserControlled</cameraMode>
      <memoryLifetime>4</memoryLifetime>
      <coefficientOfRestitution>0.4</coefficientOfRestitution>
      <friction>0.95</friction>
      <lightRange>10</lightRange>
      <stayAboveWater>false</stayAboveWater>
      <maxCreated>100</maxCreated>
      <rescale>1</rescale>
      <holdDistance>1</holdDistance>
      <_holdDistance>1</_holdDistance>
      <mass>10</mass>
      <heightOffset>-666</heightOffset>
      <nearByDistance>5</nearByDistance>
      <farAwayDistance>15</farAwayDistance>
    </parameters>
    <version>1</version>
    <typename>Octopus</typename>
  </actor>
  <actor>
    <position>
      <X>-2.11701822</X>
      <Y>15.2105179</Y>
      <Z>5.087358</Z>
    </position>
    <orientation>1.73329759</orientation>
    <heightOffset>0</heightOffset>
    <color>Green</color>
    <tintable>true</tintable>
    <creatableId>00000000-0000-0000-0000-000000000000</creatableId>
    <creatableName>Дерево 2</creatableName>
    <brain StartTaskId="-1" ActiveTaskId="-1">
      <uniqueNum>4681</uniqueNum>
      <tasks>
        <Task upid="task.managed0">
          <reflexes />
        </Task>
        <Task upid="task.managed1">
          <reflexes />
        </Task>
        <Task upid="task.managed2">
          <reflexes />
        </Task>
        <Task upid="task.managed3">
          <reflexes />
        </Task>
        <Task upid="task.managed4">
          <reflexes />
        </Task>
        <Task upid="task.managed5">
          <reflexes />
        </Task>
        <Task upid="task.managed6">
          <reflexes />
        </Task>
        <Task upid="task.managed7">
          <reflexes />
        </Task>
        <Task upid="task.managed8">
          <reflexes />
        </Task>
        <Task upid="task.managed9">
          <reflexes />
        </Task>
        <Task upid="task.managed10">
          <reflexes />
        </Task>
        <Task upid="task.managed11">
          <reflexes />
        </Task>
      </tasks>
    </brain>
    <parameters>
      <uniqueNum>3812</uniqueNum>
      <immobile>false</immobile>
      <immobileNoRot>false</immobileNoRot>
      <invulnerable>false</invulnerable>
      <showSensors>false</showSensors>
      <showHitPoints>false</showHitPoints>
      <creatable>false</creatable>
      <mute>false</mute>
      <maxHitPoints>50</maxHitPoints>
      <blipDamage>5</blipDamage>
      <missileDamage>50</missileDamage>
      <movementSpeedModifier>1</movementSpeedModifier>
      <turningSpeedModifier>1</turningSpeedModifier>
      <linearAccelerationModifier>1</linearAccelerationModifier>
      <turningAccelerationModifier>1</turningAccelerationModifier>
      <verticalSpeedModifier>1</verticalSpeedModifier>
      <verticalAccelerationModifier>1</verticalAccelerationModifier>
      <blipReloadTime>0.05</blipReloadTime>
      <blipSpeed>10</blipSpeed>
      <blipRange>35</blipRange>
      <blipsInAir>40</blipsInAir>
      <beamReloadTime>0.025</beamReloadTime>
      <beamSpeed>10</beamSpeed>
      <beamDist>35</beamDist>
      <beamsInAir>2000</beamsInAir>
      <revealed>false</revealed>
      <missileReloadTime>3</missileReloadTime>
      <missileSpeed>6</missileSpeed>
      <missileRange>50</missileRange>
      <missilesInAir>4</missilesInAir>
      <missileTrails>true</missileTrails>
      <shieldEffects>true</shieldEffects>
      <invisible>false</invisible>
      <ignored>false</ignored>
      <camouflaged>false</camouflaged>
      <pushRange>15</pushRange>
      <pushStrength>50</pushStrength>
      <kickStrength>10</kickStrength>
      <kickRate>2</kickRate>
      <hearing>1</hearing>
      <loudness>1</loudness>
      <glowAmt>1</glowAmt>
      <glowLights>0</glowLights>
      <glowEmission>0</glowEmission>
      <displayLOS>false</displayLOS>
      <displayLOP>false</displayLOP>
      <displayCurrentPage>false</displayCurrentPage>
      <cameraMode>UserControlled</cameraMode>
      <memoryLifetime>4</memoryLifetime>
      <coefficientOfRestitution>0.8</coefficientOfRestitution>
      <friction>0.5</friction>
      <lightRange>10</lightRange>
      <stayAboveWater>false</stayAboveWater>
      <maxCreated>100</maxCreated>
      <rescale>1</rescale>
      <holdDistance>1</holdDistance>
      <_holdDistance>1</_holdDistance>
      <mass>500</mass>
      <heightOffset>-666</heightOffset>
      <nearByDistance>5</nearByDistance>
      <farAwayDistance>15</farAwayDistance>
    </parameters>
    <version>1</version>
    <typename>Yucca1</typename>
  </actor>
  <actor>
    <position>
      <X>-2.04203033</X>
      <Y>11.892437</Y>
      <Z>5.85336065</Z>
    </position>
    <orientation>3.15899062</orientation>
    <heightOffset>0</heightOffset>
    <color>Green</color>
    <tintable>true</tintable>
    <creatableId>00000000-0000-0000-0000-000000000000</creatableId>
    <creatableName>Дерево 3</creatableName>
    <brain StartTaskId="-1" ActiveTaskId="-1">
      <uniqueNum>4682</uniqueNum>
      <tasks>
        <Task upid="task.managed0">
          <reflexes />
        </Task>
        <Task upid="task.managed1">
          <reflexes />
        </Task>
        <Task upid="task.managed2">
          <reflexes />
        </Task>
        <Task upid="task.managed3">
          <reflexes />
        </Task>
        <Task upid="task.managed4">
          <reflexes />
        </Task>
        <Task upid="task.managed5">
          <reflexes />
        </Task>
        <Task upid="task.managed6">
          <reflexes />
        </Task>
        <Task upid="task.managed7">
          <reflexes />
        </Task>
        <Task upid="task.managed8">
          <reflexes />
        </Task>
        <Task upid="task.managed9">
          <reflexes />
        </Task>
        <Task upid="task.managed10">
          <reflexes />
        </Task>
        <Task upid="task.managed11">
          <reflexes />
        </Task>
      </tasks>
    </brain>
    <parameters>
      <uniqueNum>3868</uniqueNum>
      <immobile>false</immobile>
      <immobileNoRot>false</immobileNoRot>
      <invulnerable>false</invulnerable>
      <showSensors>false</showSensors>
      <showHitPoints>false</showHitPoints>
      <creatable>false</creatable>
      <mute>false</mute>
      <maxHitPoints>50</maxHitPoints>
      <blipDamage>5</blipDamage>
      <missileDamage>50</missileDamage>
      <movementSpeedModifier>1</movementSpeedModifier>
      <turningSpeedModifier>1</turningSpeedModifier>
      <linearAccelerationModifier>1</linearAccelerationModifier>
      <turningAccelerationModifier>1</turningAccelerationModifier>
      <verticalSpeedModifier>1</verticalSpeedModifier>
      <verticalAccelerationModifier>1</verticalAccelerationModifier>
      <blipReloadTime>0.05</blipReloadTime>
      <blipSpeed>10</blipSpeed>
      <blipRange>35</blipRange>
      <blipsInAir>40</blipsInAir>
      <beamReloadTime>0.025</beamReloadTime>
      <beamSpeed>10</beamSpeed>
      <beamDist>35</beamDist>
      <beamsInAir>2000</beamsInAir>
      <revealed>false</revealed>
      <missileReloadTime>3</missileReloadTime>
      <missileSpeed>6</missileSpeed>
      <missileRange>50</missileRange>
      <missilesInAir>4</missilesInAir>
      <missileTrails>true</missileTrails>
      <shieldEffects>true</shieldEffects>
      <invisible>false</invisible>
      <ignored>false</ignored>
      <camouflaged>false</camouflaged>
      <pushRange>15</pushRange>
      <pushStrength>50</pushStrength>
      <kickStrength>10</kickStrength>
      <kickRate>2</kickRate>
      <hearing>1</hearing>
      <loudness>1</loudness>
      <glowAmt>1</glowAmt>
      <glowLights>0</glowLights>
      <glowEmission>0</glowEmission>
      <displayLOS>false</displayLOS>
      <displayLOP>false</displayLOP>
      <displayCurrentPage>false</displayCurrentPage>
      <cameraMode>UserControlled</cameraMode>
      <memoryLifetime>4</memoryLifetime>
      <coefficientOfRestitution>0.8</coefficientOfRestitution>
      <friction>0.5</friction>
      <lightRange>10</lightRange>
      <stayAboveWater>false</stayAboveWater>
      <maxCreated>100</maxCreated>
      <rescale>1</rescale>
      <holdDistance>1</holdDistance>
      <_holdDistance>1</_holdDistance>
      <mass>500</mass>
      <heightOffset>-666</heightOffset>
      <nearByDistance>5</nearByDistance>
      <farAwayDistance>15</farAwayDistance>
    </parameters>
    <version>1</version>
    <typename>Yucca1</typename>
  </actor>
  <actor>
    <position>
      <X>-4.22709656</X>
      <Y>11.5956469</Y>
      <Z>6.38437462</Z>
    </position>
    <orientation>2.503284</orientation>
    <heightOffset>0</heightOffset>
    <color>Green</color>
    <tintable>true</tintable>
    <creatableId>00000000-0000-0000-0000-000000000000</creatableId>
    <creatableName>Дерево 1</creatableName>
    <brain StartTaskId="-1" ActiveTaskId="-1">
      <uniqueNum>4683</uniqueNum>
      <tasks>
        <Task upid="task.managed0">
          <reflexes />
        </Task>
        <Task upid="task.managed1">
          <reflexes />
        </Task>
        <Task upid="task.managed2">
          <reflexes />
        </Task>
        <Task upid="task.managed3">
          <reflexes />
        </Task>
        <Task upid="task.managed4">
          <reflexes />
        </Task>
        <Task upid="task.managed5">
          <reflexes />
        </Task>
        <Task upid="task.managed6">
          <reflexes />
        </Task>
        <Task upid="task.managed7">
          <reflexes />
        </Task>
        <Task upid="task.managed8">
          <reflexes />
        </Task>
        <Task upid="task.managed9">
          <reflexes />
        </Task>
        <Task upid="task.managed10">
          <reflexes />
        </Task>
        <Task upid="task.managed11">
          <reflexes />
        </Task>
      </tasks>
    </brain>
    <parameters>
      <uniqueNum>3908</uniqueNum>
      <immobile>false</immobile>
      <immobileNoRot>false</immobileNoRot>
      <invulnerable>false</invulnerable>
      <showSensors>false</showSensors>
      <showHitPoints>false</showHitPoints>
      <creatable>false</creatable>
      <mute>false</mute>
      <maxHitPoints>50</maxHitPoints>
      <blipDamage>5</blipDamage>
      <missileDamage>50</missileDamage>
      <movementSpeedModifier>1</movementSpeedModifier>
      <turningSpeedModifier>1</turningSpeedModifier>
      <linearAccelerationModifier>1</linearAccelerationModifier>
      <turningAccelerationModifier>1</turningAccelerationModifier>
      <verticalSpeedModifier>1</verticalSpeedModifier>
      <verticalAccelerationModifier>1</verticalAccelerationModifier>
      <blipReloadTime>0.05</blipReloadTime>
      <blipSpeed>10</blipSpeed>
      <blipRange>35</blipRange>
      <blipsInAir>40</blipsInAir>
      <beamReloadTime>0.025</beamReloadTime>
      <beamSpeed>10</beamSpeed>
      <beamDist>35</beamDist>
      <beamsInAir>2000</beamsInAir>
      <revealed>false</revealed>
      <missileReloadTime>3</missileReloadTime>
      <missileSpeed>6</missileSpeed>
      <missileRange>50</missileRange>
      <missilesInAir>4</missilesInAir>
      <missileTrails>true</missileTrails>
      <shieldEffects>true</shieldEffects>
      <invisible>false</invisible>
      <ignored>false</ignored>
      <camouflaged>false</camouflaged>
      <pushRange>15</pushRange>
      <pushStrength>50</pushStrength>
      <kickStrength>10</kickStrength>
      <kickRate>2</kickRate>
      <hearing>1</hearing>
      <loudness>1</loudness>
      <glowAmt>1</glowAmt>
      <glowLights>0</glowLights>
      <glowEmission>0</glowEmission>
      <displayLOS>false</displayLOS>
      <displayLOP>false</displayLOP>
      <displayCurrentPage>false</displayCurrentPage>
      <cameraMode>UserControlled</cameraMode>
      <memoryLifetime>4</memoryLifetime>
      <coefficientOfRestitution>0.8</coefficientOfRestitution>
      <friction>0.5</friction>
      <lightRange>10</lightRange>
      <stayAboveWater>false</stayAboveWater>
      <maxCreated>100</maxCreated>
      <rescale>1</rescale>
      <holdDistance>1</holdDistance>
      <_holdDistance>1</_holdDistance>
      <mass>500</mass>
      <heightOffset>-666</heightOffset>
      <nearByDistance>5</nearByDistance>
      <farAwayDistance>15</farAwayDistance>
    </parameters>
    <version>1</version>
    <typename>Yucca2</typename>
  </actor>
  <actor>
    <position>
      <X>-15.3942013</X>
      <Y>9.154265</Y>
      <Z>0.485236883</Z>
    </position>
    <orientation>1.69718146</orientation>
    <heightOffset>0</heightOffset>
    <color>Green</color>
    <tintable>true</tintable>
    <creatableId>00000000-0000-0000-0000-000000000000</creatableId>
    <creatableName>Sea Grass 1</creatableName>
    <brain StartTaskId="-1" ActiveTaskId="-1">
      <uniqueNum>4684</uniqueNum>
      <tasks>
        <Task upid="task.managed0">
          <reflexes />
        </Task>
        <Task upid="task.managed1">
          <reflexes />
        </Task>
        <Task upid="task.managed2">
          <reflexes />
        </Task>
        <Task upid="task.managed3">
          <reflexes />
        </Task>
        <Task upid="task.managed4">
          <reflexes />
        </Task>
        <Task upid="task.managed5">
          <reflexes />
        </Task>
        <Task upid="task.managed6">
          <reflexes />
        </Task>
        <Task upid="task.managed7">
          <reflexes />
        </Task>
        <Task upid="task.managed8">
          <reflexes />
        </Task>
        <Task upid="task.managed9">
          <reflexes />
        </Task>
        <Task upid="task.managed10">
          <reflexes />
        </Task>
        <Task upid="task.managed11">
          <reflexes />
        </Task>
      </tasks>
    </brain>
    <parameters>
      <uniqueNum>3958</uniqueNum>
      <immobile>false</immobile>
      <immobileNoRot>false</immobileNoRot>
      <invulnerable>false</invulnerable>
      <showSensors>false</showSensors>
      <showHitPoints>false</showHitPoints>
      <creatable>false</creatable>
      <mute>false</mute>
      <maxHitPoints>50</maxHitPoints>
      <blipDamage>5</blipDamage>
      <missileDamage>50</missileDamage>
      <movementSpeedModifier>1</movementSpeedModifier>
      <turningSpeedModifier>1</turningSpeedModifier>
      <linearAccelerationModifier>1</linearAccelerationModifier>
      <turningAccelerationModifier>1</turningAccelerationModifier>
      <verticalSpeedModifier>1</verticalSpeedModifier>
      <verticalAccelerationModifier>1</verticalAccelerationModifier>
      <blipReloadTime>0.05</blipReloadTime>
      <blipSpeed>10</blipSpeed>
      <blipRange>35</blipRange>
      <blipsInAir>40</blipsInAir>
      <beamReloadTime>0.025</beamReloadTime>
      <beamSpeed>10</beamSpeed>
      <beamDist>35</beamDist>
      <beamsInAir>2000</beamsInAir>
      <revealed>false</revealed>
      <missileReloadTime>3</missileReloadTime>
      <missileSpeed>6</missileSpeed>
      <missileRange>50</missileRange>
      <missilesInAir>4</missilesInAir>
      <missileTrails>true</missileTrails>
      <shieldEffects>true</shieldEffects>
      <invisible>false</invisible>
      <ignored>false</ignored>
      <camouflaged>false</camouflaged>
      <pushRange>15</pushRange>
      <pushStrength>50</pushStrength>
      <kickStrength>10</kickStrength>
      <kickRate>2</kickRate>
      <hearing>1</hearing>
      <loudness>1</loudness>
      <glowAmt>1</glowAmt>
      <glowLights>0</glowLights>
      <glowEmission>0</glowEmission>
      <displayLOS>false</displayLOS>
      <displayLOP>false</displayLOP>
      <displayCurrentPage>false</displayCurrentPage>
      <cameraMode>UserControlled</cameraMode>
      <memoryLifetime>4</memoryLifetime>
      <coefficientOfRestitution>0.8</coefficientOfRestitution>
      <friction>0.5</friction>
      <lightRange>10</lightRange>
      <stayAboveWater>false</stayAboveWater>
      <maxCreated>100</maxCreated>
      <rescale>1</rescale>
      <holdDistance>1</holdDistance>
      <_holdDistance>1</_holdDistance>
      <mass>500</mass>
      <heightOffset>-666</heightOffset>
      <nearByDistance>5</nearByDistance>
      <farAwayDistance>15</farAwayDistance>
    </parameters>
    <version>1</version>
    <typename>Seagrass</typename>
  </actor>
  <actor>
    <position>
      <X>-12.1344719</X>
      <Y>16.1512184</Y>
      <Z>0.714122236</Z>
    </position>
    <orientation>1.69718146</orientation>
    <heightOffset>0</heightOffset>
    <color>Green</color>
    <tintable>true</tintable>
    <creatableId>00000000-0000-0000-0000-000000000000</creatableId>
    <creatableName>Sea Grass 2</creatableName>
    <brain StartTaskId="-1" ActiveTaskId="-1">
      <uniqueNum>4685</uniqueNum>
      <tasks>
        <Task upid="task.managed0">
          <reflexes />
        </Task>
        <Task upid="task.managed1">
          <reflexes />
        </Task>
        <Task upid="task.managed2">
          <reflexes />
        </Task>
        <Task upid="task.managed3">
          <reflexes />
        </Task>
        <Task upid="task.managed4">
          <reflexes />
        </Task>
        <Task upid="task.managed5">
          <reflexes />
        </Task>
        <Task upid="task.managed6">
          <reflexes />
        </Task>
        <Task upid="task.managed7">
          <reflexes />
        </Task>
        <Task upid="task.managed8">
          <reflexes />
        </Task>
        <Task upid="task.managed9">
          <reflexes />
        </Task>
        <Task upid="task.managed10">
          <reflexes />
        </Task>
        <Task upid="task.managed11">
          <reflexes />
        </Task>
      </tasks>
    </brain>
    <parameters>
      <uniqueNum>3983</uniqueNum>
      <immobile>false</immobile>
      <immobileNoRot>false</immobileNoRot>
      <invulnerable>false</invulnerable>
      <showSensors>false</showSensors>
      <showHitPoints>false</showHitPoints>
      <creatable>false</creatable>
      <mute>false</mute>
      <maxHitPoints>50</maxHitPoints>
      <blipDamage>5</blipDamage>
      <missileDamage>50</missileDamage>
      <movementSpeedModifier>1</movementSpeedModifier>
      <turningSpeedModifier>1</turningSpeedModifier>
      <linearAccelerationModifier>1</linearAccelerationModifier>
      <turningAccelerationModifier>1</turningAccelerationModifier>
      <verticalSpeedModifier>1</verticalSpeedModifier>
      <verticalAccelerationModifier>1</verticalAccelerationModifier>
      <blipReloadTime>0.05</blipReloadTime>
      <blipSpeed>10</blipSpeed>
      <blipRange>35</blipRange>
      <blipsInAir>40</blipsInAir>
      <beamReloadTime>0.025</beamReloadTime>
      <beamSpeed>10</beamSpeed>
      <beamDist>35</beamDist>
      <beamsInAir>2000</beamsInAir>
      <revealed>false</revealed>
      <missileReloadTime>3</missileReloadTime>
      <missileSpeed>6</missileSpeed>
      <missileRange>50</missileRange>
      <missilesInAir>4</missilesInAir>
      <missileTrails>true</missileTrails>
      <shieldEffects>true</shieldEffects>
      <invisible>false</invisible>
      <ignored>false</ignored>
      <camouflaged>false</camouflaged>
      <pushRange>15</pushRange>
      <pushStrength>50</pushStrength>
      <kickStrength>10</kickStrength>
      <kickRate>2</kickRate>
      <hearing>1</hearing>
      <loudness>1</loudness>
      <glowAmt>1</glowAmt>
      <glowLights>0</glowLights>
      <glowEmission>0</glowEmission>
      <displayLOS>false</displayLOS>
      <displayLOP>false</displayLOP>
      <displayCurrentPage>false</displayCurrentPage>
      <cameraMode>UserControlled</cameraMode>
      <memoryLifetime>4</memoryLifetime>
      <coefficientOfRestitution>0.8</coefficientOfRestitution>
      <friction>0.5</friction>
      <lightRange>10</lightRange>
      <stayAboveWater>false</stayAboveWater>
      <maxCreated>100</maxCreated>
      <rescale>1</rescale>
      <holdDistance>1</holdDistance>
      <_holdDistance>1</_holdDistance>
      <mass>500</mass>
      <heightOffset>-666</heightOffset>
      <nearByDistance>5</nearByDistance>
      <farAwayDistance>15</farAwayDistance>
    </parameters>
    <version>1</version>
    <typename>Seagrass</typename>
  </actor>
  <actor>
    <position>
      <X>-3.12764454</X>
      <Y>3.08595943</Y>
      <Z>0.247196153</Z>
    </position>
    <orientation>1.69718146</orientation>
    <heightOffset>0</heightOffset>
    <color>Green</color>
    <tintable>true</tintable>
    <creatableId>00000000-0000-0000-0000-000000000000</creatableId>
    <creatableName>Sea Grass 3</creatableName>
    <brain StartTaskId="-1" ActiveTaskId="-1">
      <uniqueNum>4686</uniqueNum>
      <tasks>
        <Task upid="task.managed0">
          <reflexes />
        </Task>
        <Task upid="task.managed1">
          <reflexes />
        </Task>
        <Task upid="task.managed2">
          <reflexes />
        </Task>
        <Task upid="task.managed3">
          <reflexes />
        </Task>
        <Task upid="task.managed4">
          <reflexes />
        </Task>
        <Task upid="task.managed5">
          <reflexes />
        </Task>
        <Task upid="task.managed6">
          <reflexes />
        </Task>
        <Task upid="task.managed7">
          <reflexes />
        </Task>
        <Task upid="task.managed8">
          <reflexes />
        </Task>
        <Task upid="task.managed9">
          <reflexes />
        </Task>
        <Task upid="task.managed10">
          <reflexes />
        </Task>
        <Task upid="task.managed11">
          <reflexes />
        </Task>
      </tasks>
    </brain>
    <parameters>
      <uniqueNum>4016</uniqueNum>
      <immobile>false</immobile>
      <immobileNoRot>false</immobileNoRot>
      <invulnerable>false</invulnerable>
      <showSensors>false</showSensors>
      <showHitPoints>false</showHitPoints>
      <creatable>false</creatable>
      <mute>false</mute>
      <maxHitPoints>50</maxHitPoints>
      <blipDamage>5</blipDamage>
      <missileDamage>50</missileDamage>
      <movementSpeedModifier>1</movementSpeedModifier>
      <turningSpeedModifier>1</turningSpeedModifier>
      <linearAccelerationModifier>1</linearAccelerationModifier>
      <turningAccelerationModifier>1</turningAccelerationModifier>
      <verticalSpeedModifier>1</verticalSpeedModifier>
      <verticalAccelerationModifier>1</verticalAccelerationModifier>
      <blipReloadTime>0.05</blipReloadTime>
      <blipSpeed>10</blipSpeed>
      <blipRange>35</blipRange>
      <blipsInAir>40</blipsInAir>
      <beamReloadTime>0.025</beamReloadTime>
      <beamSpeed>10</beamSpeed>
      <beamDist>35</beamDist>
      <beamsInAir>2000</beamsInAir>
      <revealed>false</revealed>
      <missileReloadTime>3</missileReloadTime>
      <missileSpeed>6</missileSpeed>
      <missileRange>50</missileRange>
      <missilesInAir>4</missilesInAir>
      <missileTrails>true</missileTrails>
      <shieldEffects>true</shieldEffects>
      <invisible>false</invisible>
      <ignored>false</ignored>
      <camouflaged>false</camouflaged>
      <pushRange>15</pushRange>
      <pushStrength>50</pushStrength>
      <kickStrength>10</kickStrength>
      <kickRate>2</kickRate>
      <hearing>1</hearing>
      <loudness>1</loudness>
      <glowAmt>1</glowAmt>
      <glowLights>0</glowLights>
      <glowEmission>0</glowEmission>
      <displayLOS>false</displayLOS>
      <displayLOP>false</displayLOP>
      <displayCurrentPage>false</displayCurrentPage>
      <cameraMode>UserControlled</cameraMode>
      <memoryLifetime>4</memoryLifetime>
      <coefficientOfRestitution>0.8</coefficientOfRestitution>
      <friction>0.5</friction>
      <lightRange>10</lightRange>
      <stayAboveWater>false</stayAboveWater>
      <maxCreated>100</maxCreated>
      <rescale>1</rescale>
      <holdDistance>1</holdDistance>
      <_holdDistance>1</_holdDistance>
      <mass>500</mass>
      <heightOffset>-666</heightOffset>
      <nearByDistance>5</nearByDistance>
      <farAwayDistance>15</farAwayDistance>
    </parameters>
    <version>1</version>
    <typename>Seagrass</typename>
  </actor>
  <actor>
    <position>
      <X>3.30088878</X>
      <Y>5.30346727</Y>
      <Z>0.247196153</Z>
    </position>
    <orientation>1.69718146</orientation>
    <heightOffset>0</heightOffset>
    <color>Green</color>
    <tintable>true</tintable>
    <creatableId>00000000-0000-0000-0000-000000000000</creatableId>
    <creatableName>Sea Grass 4</creatableName>
    <brain StartTaskId="-1" ActiveTaskId="-1">
      <uniqueNum>4687</uniqueNum>
      <tasks>
        <Task upid="task.managed0">
          <reflexes />
        </Task>
        <Task upid="task.managed1">
          <reflexes />
        </Task>
        <Task upid="task.managed2">
          <reflexes />
        </Task>
        <Task upid="task.managed3">
          <reflexes />
        </Task>
        <Task upid="task.managed4">
          <reflexes />
        </Task>
        <Task upid="task.managed5">
          <reflexes />
        </Task>
        <Task upid="task.managed6">
          <reflexes />
        </Task>
        <Task upid="task.managed7">
          <reflexes />
        </Task>
        <Task upid="task.managed8">
          <reflexes />
        </Task>
        <Task upid="task.managed9">
          <reflexes />
        </Task>
        <Task upid="task.managed10">
          <reflexes />
        </Task>
        <Task upid="task.managed11">
          <reflexes />
        </Task>
      </tasks>
    </brain>
    <parameters>
      <uniqueNum>4041</uniqueNum>
      <immobile>false</immobile>
      <immobileNoRot>false</immobileNoRot>
      <invulnerable>false</invulnerable>
      <showSensors>false</showSensors>
      <showHitPoints>false</showHitPoints>
      <creatable>false</creatable>
      <mute>false</mute>
      <maxHitPoints>50</maxHitPoints>
      <blipDamage>5</blipDamage>
      <missileDamage>50</missileDamage>
      <movementSpeedModifier>1</movementSpeedModifier>
      <turningSpeedModifier>1</turningSpeedModifier>
      <linearAccelerationModifier>1</linearAccelerationModifier>
      <turningAccelerationModifier>1</turningAccelerationModifier>
      <verticalSpeedModifier>1</verticalSpeedModifier>
      <verticalAccelerationModifier>1</verticalAccelerationModifier>
      <blipReloadTime>0.05</blipReloadTime>
      <blipSpeed>10</blipSpeed>
      <blipRange>35</blipRange>
      <blipsInAir>40</blipsInAir>
      <beamReloadTime>0.025</beamReloadTime>
      <beamSpeed>10</beamSpeed>
      <beamDist>35</beamDist>
      <beamsInAir>2000</beamsInAir>
      <revealed>false</revealed>
      <missileReloadTime>3</missileReloadTime>
      <missileSpeed>6</missileSpeed>
      <missileRange>50</missileRange>
      <missilesInAir>4</missilesInAir>
      <missileTrails>true</missileTrails>
      <shieldEffects>true</shieldEffects>
      <invisible>false</invisible>
      <ignored>false</ignored>
      <camouflaged>false</camouflaged>
      <pushRange>15</pushRange>
      <pushStrength>50</pushStrength>
      <kickStrength>10</kickStrength>
      <kickRate>2</kickRate>
      <hearing>1</hearing>
      <loudness>1</loudness>
      <glowAmt>1</glowAmt>
      <glowLights>0</glowLights>
      <glowEmission>0</glowEmission>
      <displayLOS>false</displayLOS>
      <displayLOP>false</displayLOP>
      <displayCurrentPage>false</displayCurrentPage>
      <cameraMode>UserControlled</cameraMode>
      <memoryLifetime>4</memoryLifetime>
      <coefficientOfRestitution>0.8</coefficientOfRestitution>
      <friction>0.5</friction>
      <lightRange>10</lightRange>
      <stayAboveWater>false</stayAboveWater>
      <maxCreated>100</maxCreated>
      <rescale>1</rescale>
      <holdDistance>1</holdDistance>
      <_holdDistance>1</_holdDistance>
      <mass>500</mass>
      <heightOffset>-666</heightOffset>
      <nearByDistance>5</nearByDistance>
      <farAwayDistance>15</farAwayDistance>
    </parameters>
    <version>1</version>
    <typename>Seagrass</typename>
  </actor>
  <actor>
    <position>
      <X>-15.1956129</X>
      <Y>15.8622818</Y>
      <Z>2.613125</Z>
    </position>
    <orientation>1.69718146</orientation>
    <heightOffset>0</heightOffset>
    <color>Purple</color>
    <tintable>true</tintable>
    <creatableId>00000000-0000-0000-0000-000000000000</creatableId>
    <creatableName>Лодка 1</creatableName>
    <brain StartTaskId="-1" ActiveTaskId="-1">
      <uniqueNum>4688</uniqueNum>
      <tasks>
        <Task upid="task.managed0">
          <reflexes />
        </Task>
        <Task upid="task.managed1">
          <reflexes />
        </Task>
        <Task upid="task.managed2">
          <reflexes />
        </Task>
        <Task upid="task.managed3">
          <reflexes />
        </Task>
        <Task upid="task.managed4">
          <reflexes />
        </Task>
        <Task upid="task.managed5">
          <reflexes />
        </Task>
        <Task upid="task.managed6">
          <reflexes />
        </Task>
        <Task upid="task.managed7">
          <reflexes />
        </Task>
        <Task upid="task.managed8">
          <reflexes />
        </Task>
        <Task upid="task.managed9">
          <reflexes />
        </Task>
        <Task upid="task.managed10">
          <reflexes />
        </Task>
        <Task upid="task.managed11">
          <reflexes />
        </Task>
      </tasks>
    </brain>
    <parameters>
      <uniqueNum>4071</uniqueNum>
      <immobile>false</immobile>
      <immobileNoRot>false</immobileNoRot>
      <invulnerable>false</invulnerable>
      <showSensors>false</showSensors>
      <showHitPoints>false</showHitPoints>
      <creatable>false</creatable>
      <mute>false</mute>
      <maxHitPoints>50</maxHitPoints>
      <blipDamage>5</blipDamage>
      <missileDamage>50</missileDamage>
      <movementSpeedModifier>1</movementSpeedModifier>
      <turningSpeedModifier>1</turningSpeedModifier>
      <linearAccelerationModifier>1</linearAccelerationModifier>
      <turningAccelerationModifier>1</turningAccelerationModifier>
      <verticalSpeedModifier>1</verticalSpeedModifier>
      <verticalAccelerationModifier>1</verticalAccelerationModifier>
      <blipReloadTime>0.05</blipReloadTime>
      <blipSpeed>10</blipSpeed>
      <blipRange>35</blipRange>
      <blipsInAir>40</blipsInAir>
      <beamReloadTime>0.025</beamReloadTime>
      <beamSpeed>10</beamSpeed>
      <beamDist>35</beamDist>
      <beamsInAir>2000</beamsInAir>
      <revealed>false</revealed>
      <missileReloadTime>3</missileReloadTime>
      <missileSpeed>6</missileSpeed>
      <missileRange>50</missileRange>
      <missilesInAir>4</missilesInAir>
      <missileTrails>true</missileTrails>
      <shieldEffects>true</shieldEffects>
      <invisible>false</invisible>
      <ignored>false</ignored>
      <camouflaged>false</camouflaged>
      <pushRange>15</pushRange>
      <pushStrength>50</pushStrength>
      <kickStrength>10</kickStrength>
      <kickRate>2</kickRate>
      <hearing>1</hearing>
      <loudness>1</loudness>
      <glowAmt>1</glowAmt>
      <glowLights>0</glowLights>
      <glowEmission>0</glowEmission>
      <displayLOS>false</displayLOS>
      <displayLOP>false</displayLOP>
      <displayCurrentPage>false</displayCurrentPage>
      <cameraMode>UserControlled</cameraMode>
      <memoryLifetime>4</memoryLifetime>
      <coefficientOfRestitution>0.1</coefficientOfRestitution>
      <friction>0.5</friction>
      <lightRange>10</lightRange>
      <stayAboveWater>true</stayAboveWater>
      <maxCreated>100</maxCreated>
      <rescale>1</rescale>
      <holdDistance>1</holdDistance>
      <_holdDistance>1</_holdDistance>
      <mass>500</mass>
      <heightOffset>-666</heightOffset>
      <nearByDistance>5</nearByDistance>
      <farAwayDistance>15</farAwayDistance>
    </parameters>
    <version>1</version>
    <typename>FloatBot</typename>
  </actor>
  <actor>
    <position>
      <X>-13.137207</X>
      <Y>14.2695637</Y>
      <Z>3.613125</Z>
    </position>
    <orientation>1.69718146</orientation>
    <heightOffset>0</heightOffset>
    <color>White</color>
    <tintable>true</tintable>
    <creatableId>00000000-0000-0000-0000-000000000000</creatableId>
    <creatableName>Черепашка 1</creatableName>
    <brain StartTaskId="-1" ActiveTaskId="-1">
      <uniqueNum>4689</uniqueNum>
      <tasks>
        <Task upid="task.managed0">
          <reflexes />
        </Task>
        <Task upid="task.managed1">
          <reflexes />
        </Task>
        <Task upid="task.managed2">
          <reflexes />
        </Task>
        <Task upid="task.managed3">
          <reflexes />
        </Task>
        <Task upid="task.managed4">
          <reflexes />
        </Task>
        <Task upid="task.managed5">
          <reflexes />
        </Task>
        <Task upid="task.managed6">
          <reflexes />
        </Task>
        <Task upid="task.managed7">
          <reflexes />
        </Task>
        <Task upid="task.managed8">
          <reflexes />
        </Task>
        <Task upid="task.managed9">
          <reflexes />
        </Task>
        <Task upid="task.managed10">
          <reflexes />
        </Task>
        <Task upid="task.managed11">
          <reflexes />
        </Task>
      </tasks>
    </brain>
    <parameters>
      <uniqueNum>4112</uniqueNum>
      <immobile>false</immobile>
      <immobileNoRot>false</immobileNoRot>
      <invulnerable>false</invulnerable>
      <showSensors>false</showSensors>
      <showHitPoints>false</showHitPoints>
      <creatable>false</creatable>
      <mute>false</mute>
      <maxHitPoints>50</maxHitPoints>
      <blipDamage>5</blipDamage>
      <missileDamage>50</missileDamage>
      <movementSpeedModifier>1</movementSpeedModifier>
      <turningSpeedModifier>1</turningSpeedModifier>
      <linearAccelerationModifier>1</linearAccelerationModifier>
      <turningAccelerationModifier>1</turningAccelerationModifier>
      <verticalSpeedModifier>1</verticalSpeedModifier>
      <verticalAccelerationModifier>1</verticalAccelerationModifier>
      <blipReloadTime>0.05</blipReloadTime>
      <blipSpeed>10</blipSpeed>
      <blipRange>35</blipRange>
      <blipsInAir>40</blipsInAir>
      <beamReloadTime>0.025</beamReloadTime>
      <beamSpeed>10</beamSpeed>
      <beamDist>35</beamDist>
      <beamsInAir>2000</beamsInAir>
      <revealed>false</revealed>
      <missileReloadTime>3</missileReloadTime>
      <missileSpeed>6</missileSpeed>
      <missileRange>50</missileRange>
      <missilesInAir>4</missilesInAir>
      <missileTrails>true</missileTrails>
      <shieldEffects>true</shieldEffects>
      <invisible>false</invisible>
      <ignored>false</ignored>
      <camouflaged>false</camouflaged>
      <pushRange>15</pushRange>
      <pushStrength>50</pushStrength>
      <kickStrength>10</kickStrength>
      <kickRate>2</kickRate>
      <hearing>1</hearing>
      <loudness>1</loudness>
      <glowAmt>1</glowAmt>
      <glowLights>0</glowLights>
      <glowEmission>0</glowEmission>
      <displayLOS>false</displayLOS>
      <displayLOP>false</displayLOP>
      <displayCurrentPage>false</displayCurrentPage>
      <cameraMode>UserControlled</cameraMode>
      <memoryLifetime>4</memoryLifetime>
      <coefficientOfRestitution>0.8</coefficientOfRestitution>
      <friction>0.5</friction>
      <lightRange>10</lightRange>
      <stayAboveWater>true</stayAboveWater>
      <maxCreated>100</maxCreated>
      <rescale>1</rescale>
      <holdDistance>1</holdDistance>
      <_holdDistance>1</_holdDistance>
      <mass>10</mass>
      <heightOffset>-666</heightOffset>
      <nearByDistance>5</nearByDistance>
      <farAwayDistance>15</farAwayDistance>
    </parameters>
    <version>1</version>
    <typename>Turtle</typename>
  </actor>
  <actor>
    <position>
      <X>-1.68220377</X>
      <Y>-7.315384</Y>
      <Z>5</Z>
    </position>
    <orientation>1.69718146</orientation>
    <heightOffset>0</heightOffset>
    <color>White</color>
    <tintable>true</tintable>
    <creatableId>00000000-0000-0000-0000-000000000000</creatableId>
    <creatableName>Блюдце 1</creatableName>
    <brain StartTaskId="-1" ActiveTaskId="-1">
      <uniqueNum>4690</uniqueNum>
      <tasks>
        <Task upid="task.managed0">
          <reflexes />
        </Task>
        <Task upid="task.managed1">
          <reflexes />
        </Task>
        <Task upid="task.managed2">
          <reflexes />
        </Task>
        <Task upid="task.managed3">
          <reflexes />
        </Task>
        <Task upid="task.managed4">
          <reflexes />
        </Task>
        <Task upid="task.managed5">
          <reflexes />
        </Task>
        <Task upid="task.managed6">
          <reflexes />
        </Task>
        <Task upid="task.managed7">
          <reflexes />
        </Task>
        <Task upid="task.managed8">
          <reflexes />
        </Task>
        <Task upid="task.managed9">
          <reflexes />
        </Task>
        <Task upid="task.managed10">
          <reflexes />
        </Task>
        <Task upid="task.managed11">
          <reflexes />
        </Task>
      </tasks>
    </brain>
    <parameters>
      <uniqueNum>4142</uniqueNum>
      <immobile>false</immobile>
      <immobileNoRot>false</immobileNoRot>
      <invulnerable>false</invulnerable>
      <showSensors>false</showSensors>
      <showHitPoints>false</showHitPoints>
      <creatable>false</creatable>
      <mute>false</mute>
      <maxHitPoints>50</maxHitPoints>
      <blipDamage>5</blipDamage>
      <missileDamage>50</missileDamage>
      <movementSpeedModifier>1</movementSpeedModifier>
      <turningSpeedModifier>1</turningSpeedModifier>
      <linearAccelerationModifier>1</linearAccelerationModifier>
      <turningAccelerationModifier>1</turningAccelerationModifier>
      <verticalSpeedModifier>1</verticalSpeedModifier>
      <verticalAccelerationModifier>1</verticalAccelerationModifier>
      <blipReloadTime>0.05</blipReloadTime>
      <blipSpeed>10</blipSpeed>
      <blipRange>35</blipRange>
      <blipsInAir>40</blipsInAir>
      <beamReloadTime>0.025</beamReloadTime>
      <beamSpeed>10</beamSpeed>
      <beamDist>35</beamDist>
      <beamsInAir>2000</beamsInAir>
      <revealed>false</revealed>
      <missileReloadTime>3</missileReloadTime>
      <missileSpeed>6</missileSpeed>
      <missileRange>50</missileRange>
      <missilesInAir>4</missilesInAir>
      <missileTrails>true</missileTrails>
      <shieldEffects>true</shieldEffects>
      <invisible>false</invisible>
      <ignored>false</ignored>
      <camouflaged>false</camouflaged>
      <pushRange>15</pushRange>
      <pushStrength>50</pushStrength>
      <kickStrength>10</kickStrength>
      <kickRate>2</kickRate>
      <hearing>1</hearing>
      <loudness>1</loudness>
      <glowAmt>1</glowAmt>
      <glowLights>0</glowLights>
      <glowEmission>0</glowEmission>
      <displayLOS>false</displayLOS>
      <displayLOP>false</displayLOP>
      <displayCurrentPage>false</displayCurrentPage>
      <cameraMode>UserControlled</cameraMode>
      <memoryLifetime>4</memoryLifetime>
      <coefficientOfRestitution>0.8</coefficientOfRestitution>
      <friction>0.5</friction>
      <lightRange>10</lightRange>
      <stayAboveWater>true</stayAboveWater>
      <maxCreated>100</maxCreated>
      <rescale>1</rescale>
      <holdDistance>1</holdDistance>
      <_holdDistance>1</_holdDistance>
      <mass>20</mass>
      <heightOffset>-666</heightOffset>
      <nearByDistance>5</nearByDistance>
      <farAwayDistance>15</farAwayDistance>
    </parameters>
    <version>1</version>
    <typename>Saucer</typename>
  </actor>
  <actor>
    <position>
      <X>-10.7987671</X>
      <Y>7.864087</Y>
      <Z>2.613125</Z>
    </position>
    <orientation>1.69718146</orientation>
    <heightOffset>0</heightOffset>
    <color>Yellow</color>
    <tintable>true</tintable>
    <creatableId>00000000-0000-0000-0000-000000000000</creatableId>
    <creatableName>Лодка 2</creatableName>
    <brain StartTaskId="-1" ActiveTaskId="-1">
      <uniqueNum>4691</uniqueNum>
      <tasks>
        <Task upid="task.managed0">
          <reflexes />
        </Task>
        <Task upid="task.managed1">
          <reflexes />
        </Task>
        <Task upid="task.managed2">
          <reflexes />
        </Task>
        <Task upid="task.managed3">
          <reflexes />
        </Task>
        <Task upid="task.managed4">
          <reflexes />
        </Task>
        <Task upid="task.managed5">
          <reflexes />
        </Task>
        <Task upid="task.managed6">
          <reflexes />
        </Task>
        <Task upid="task.managed7">
          <reflexes />
        </Task>
        <Task upid="task.managed8">
          <reflexes />
        </Task>
        <Task upid="task.managed9">
          <reflexes />
        </Task>
        <Task upid="task.managed10">
          <reflexes />
        </Task>
        <Task upid="task.managed11">
          <reflexes />
        </Task>
      </tasks>
    </brain>
    <parameters>
      <uniqueNum>4195</uniqueNum>
      <immobile>false</immobile>
      <immobileNoRot>false</immobileNoRot>
      <invulnerable>false</invulnerable>
      <showSensors>false</showSensors>
      <showHitPoints>false</showHitPoints>
      <creatable>false</creatable>
      <mute>false</mute>
      <maxHitPoints>50</maxHitPoints>
      <blipDamage>5</blipDamage>
      <missileDamage>50</missileDamage>
      <movementSpeedModifier>1</movementSpeedModifier>
      <turningSpeedModifier>1</turningSpeedModifier>
      <linearAccelerationModifier>1</linearAccelerationModifier>
      <turningAccelerationModifier>1</turningAccelerationModifier>
      <verticalSpeedModifier>1</verticalSpeedModifier>
      <verticalAccelerationModifier>1</verticalAccelerationModifier>
      <blipReloadTime>0.05</blipReloadTime>
      <blipSpeed>10</blipSpeed>
      <blipRange>35</blipRange>
      <blipsInAir>40</blipsInAir>
      <beamReloadTime>0.025</beamReloadTime>
      <beamSpeed>10</beamSpeed>
      <beamDist>35</beamDist>
      <beamsInAir>2000</beamsInAir>
      <revealed>false</revealed>
      <missileReloadTime>3</missileReloadTime>
      <missileSpeed>6</missileSpeed>
      <missileRange>50</missileRange>
      <missilesInAir>4</missilesInAir>
      <missileTrails>true</missileTrails>
      <shieldEffects>true</shieldEffects>
      <invisible>false</invisible>
      <ignored>false</ignored>
      <camouflaged>false</camouflaged>
      <pushRange>15</pushRange>
      <pushStrength>50</pushStrength>
      <kickStrength>10</kickStrength>
      <kickRate>2</kickRate>
      <hearing>1</hearing>
      <loudness>1</loudness>
      <glowAmt>1</glowAmt>
      <glowLights>0</glowLights>
      <glowEmission>0</glowEmission>
      <displayLOS>false</displayLOS>
      <displayLOP>false</displayLOP>
      <displayCurrentPage>false</displayCurrentPage>
      <cameraMode>UserControlled</cameraMode>
      <memoryLifetime>4</memoryLifetime>
      <coefficientOfRestitution>0.1</coefficientOfRestitution>
      <friction>0.5</friction>
      <lightRange>10</lightRange>
      <stayAboveWater>true</stayAboveWater>
      <maxCreated>100</maxCreated>
      <rescale>1</rescale>
      <holdDistance>1</holdDistance>
      <_holdDistance>1</_holdDistance>
      <mass>500</mass>
      <heightOffset>-666</heightOffset>
      <nearByDistance>5</nearByDistance>
      <farAwayDistance>15</farAwayDistance>
    </parameters>
    <version>1</version>
    <typename>FloatBot</typename>
  </actor>
  <actor>
    <position>
      <X>-12.9851513</X>
      <Y>7.23520756</Y>
      <Z>0.527962148</Z>
    </position>
    <orientation>1.69718146</orientation>
    <heightOffset>0</heightOffset>
    <color>Orange</color>
    <tintable>true</tintable>
    <creatableId>00000000-0000-0000-0000-000000000000</creatableId>
    <creatableName>Starfish 1</creatableName>
    <brain StartTaskId="-1" ActiveTaskId="-1">
      <uniqueNum>4692</uniqueNum>
      <tasks>
        <Task upid="task.managed0">
          <reflexes />
        </Task>
        <Task upid="task.managed1">
          <reflexes />
        </Task>
        <Task upid="task.managed2">
          <reflexes />
        </Task>
        <Task upid="task.managed3">
          <reflexes />
        </Task>
        <Task upid="task.managed4">
          <reflexes />
        </Task>
        <Task upid="task.managed5">
          <reflexes />
        </Task>
        <Task upid="task.managed6">
          <reflexes />
        </Task>
        <Task upid="task.managed7">
          <reflexes />
        </Task>
        <Task upid="task.managed8">
          <reflexes />
        </Task>
        <Task upid="task.managed9">
          <reflexes />
        </Task>
        <Task upid="task.managed10">
          <reflexes />
        </Task>
        <Task upid="task.managed11">
          <reflexes />
        </Task>
      </tasks>
    </brain>
    <parameters>
      <uniqueNum>4246</uniqueNum>
      <immobile>false</immobile>
      <immobileNoRot>false</immobileNoRot>
      <invulnerable>false</invulnerable>
      <showSensors>false</showSensors>
      <showHitPoints>false</showHitPoints>
      <creatable>false</creatable>
      <mute>false</mute>
      <maxHitPoints>50</maxHitPoints>
      <blipDamage>5</blipDamage>
      <missileDamage>50</missileDamage>
      <movementSpeedModifier>1</movementSpeedModifier>
      <turningSpeedModifier>1</turningSpeedModifier>
      <linearAccelerationModifier>1</linearAccelerationModifier>
      <turningAccelerationModifier>1</turningAccelerationModifier>
      <verticalSpeedModifier>1</verticalSpeedModifier>
      <verticalAccelerationModifier>1</verticalAccelerationModifier>
      <blipReloadTime>0.05</blipReloadTime>
      <blipSpeed>10</blipSpeed>
      <blipRange>35</blipRange>
      <blipsInAir>40</blipsInAir>
      <beamReloadTime>0.025</beamReloadTime>
      <beamSpeed>10</beamSpeed>
      <beamDist>35</beamDist>
      <beamsInAir>2000</beamsInAir>
      <revealed>false</revealed>
      <missileReloadTime>3</missileReloadTime>
      <missileSpeed>6</missileSpeed>
      <missileRange>50</missileRange>
      <missilesInAir>4</missilesInAir>
      <missileTrails>true</missileTrails>
      <shieldEffects>true</shieldEffects>
      <invisible>false</invisible>
      <ignored>false</ignored>
      <camouflaged>false</camouflaged>
      <pushRange>15</pushRange>
      <pushStrength>50</pushStrength>
      <kickStrength>10</kickStrength>
      <kickRate>2</kickRate>
      <hearing>1</hearing>
      <loudness>1</loudness>
      <glowAmt>1</glowAmt>
      <glowLights>0</glowLights>
      <glowEmission>0</glowEmission>
      <displayLOS>false</displayLOS>
      <displayLOP>false</displayLOP>
      <displayCurrentPage>false</displayCurrentPage>
      <cameraMode>UserControlled</cameraMode>
      <memoryLifetime>4</memoryLifetime>
      <coefficientOfRestitution>0.8</coefficientOfRestitution>
      <friction>0.9</friction>
      <lightRange>10</lightRange>
      <stayAboveWater>false</stayAboveWater>
      <maxCreated>100</maxCreated>
      <rescale>1</rescale>
      <holdDistance>1</holdDistance>
      <_holdDistance>1</_holdDistance>
      <mass>0.1</mass>
      <heightOffset>-666</heightOffset>
      <nearByDistance>5</nearByDistance>
      <farAwayDistance>15</farAwayDistance>
    </parameters>
    <version>1</version>
    <typename>Starfish</typename>
  </actor>
  <actor>
    <position>
      <X>-15.77952</X>
      <Y>12.6591215</Y>
      <Z>1.8821851</Z>
    </position>
    <orientation>1.69718146</orientation>
    <heightOffset>0</heightOffset>
    <color>White</color>
    <tintable>true</tintable>
    <creatableId>00000000-0000-0000-0000-000000000000</creatableId>
    <creatableName>Рыба 1</creatableName>
    <brain StartTaskId="-1" ActiveTaskId="-1">
      <uniqueNum>4693</uniqueNum>
      <tasks>
        <Task upid="task.managed0">
          <reflexes />
        </Task>
        <Task upid="task.managed1">
          <reflexes />
        </Task>
        <Task upid="task.managed2">
          <reflexes />
        </Task>
        <Task upid="task.managed3">
          <reflexes />
        </Task>
        <Task upid="task.managed4">
          <reflexes />
        </Task>
        <Task upid="task.managed5">
          <reflexes />
        </Task>
        <Task upid="task.managed6">
          <reflexes />
        </Task>
        <Task upid="task.managed7">
          <reflexes />
        </Task>
        <Task upid="task.managed8">
          <reflexes />
        </Task>
        <Task upid="task.managed9">
          <reflexes />
        </Task>
        <Task upid="task.managed10">
          <reflexes />
        </Task>
        <Task upid="task.managed11">
          <reflexes />
        </Task>
      </tasks>
    </brain>
    <parameters>
      <uniqueNum>4306</uniqueNum>
      <immobile>false</immobile>
      <immobileNoRot>false</immobileNoRot>
      <invulnerable>false</invulnerable>
      <showSensors>false</showSensors>
      <showHitPoints>false</showHitPoints>
      <creatable>false</creatable>
      <mute>false</mute>
      <maxHitPoints>50</maxHitPoints>
      <blipDamage>5</blipDamage>
      <missileDamage>50</missileDamage>
      <movementSpeedModifier>1</movementSpeedModifier>
      <turningSpeedModifier>1</turningSpeedModifier>
      <linearAccelerationModifier>1</linearAccelerationModifier>
      <turningAccelerationModifier>1</turningAccelerationModifier>
      <verticalSpeedModifier>1</verticalSpeedModifier>
      <verticalAccelerationModifier>1</verticalAccelerationModifier>
      <blipReloadTime>0.05</blipReloadTime>
      <blipSpeed>10</blipSpeed>
      <blipRange>35</blipRange>
      <blipsInAir>40</blipsInAir>
      <beamReloadTime>0.025</beamReloadTime>
      <beamSpeed>10</beamSpeed>
      <beamDist>35</beamDist>
      <beamsInAir>2000</beamsInAir>
      <revealed>false</revealed>
      <missileReloadTime>3</missileReloadTime>
      <missileSpeed>6</missileSpeed>
      <missileRange>50</missileRange>
      <missilesInAir>4</missilesInAir>
      <missileTrails>true</missileTrails>
      <shieldEffects>true</shieldEffects>
      <invisible>false</invisible>
      <ignored>false</ignored>
      <camouflaged>false</camouflaged>
      <pushRange>15</pushRange>
      <pushStrength>50</pushStrength>
      <kickStrength>10</kickStrength>
      <kickRate>2</kickRate>
      <hearing>1</hearing>
      <loudness>1</loudness>
      <glowAmt>1</glowAmt>
      <glowLights>0</glowLights>
      <glowEmission>0</glowEmission>
      <displayLOS>false</displayLOS>
      <displayLOP>false</displayLOP>
      <displayCurrentPage>false</displayCurrentPage>
      <cameraMode>UserControlled</cameraMode>
      <memoryLifetime>4</memoryLifetime>
      <coefficientOfRestitution>0.8</coefficientOfRestitution>
      <friction>0.3</friction>
      <lightRange>10</lightRange>
      <stayAboveWater>false</stayAboveWater>
      <maxCreated>100</maxCreated>
      <rescale>1</rescale>
      <holdDistance>1</holdDistance>
      <_holdDistance>1</_holdDistance>
      <mass>50</mass>
      <heightOffset>-666</heightOffset>
      <nearByDistance>5</nearByDistance>
      <farAwayDistance>15</farAwayDistance>
    </parameters>
    <version>1</version>
    <typename>SwimFish</typename>
  </actor>
</XmlLevelData>